temp_path.py
temp_path-0.1.1.dist-info/WHEEL
temp_path-0.1.1.dist-info/METADATA
temp_path-0.1.1.dist-info/RECORD
