Metadata-Version: 2.1
Name: temp-path
Version: 0.1.1
Summary: A tool to temporarily add folders to the path.
Home-page: UNKNOWN
License: UNKNOWN
Author: Jan Freyberg
Author-email: jan.freyberg@gmail.com
Requires-Python: >=3.5,<4.0
Classifier: Programming Language :: Python :: 3
Classifier: Programming Language :: Python :: 3.5
Classifier: Programming Language :: Python :: 3.6
Classifier: Programming Language :: Python :: 3.7
